{
    "type": "FeatureCollection",
    "features": [
        {
            "type": "Feature",
            "geometry": {
                "type": "Point",
                "coordinates": [101.66215603483953, 15.463955499826431]
            },
            "properties": {
                "Prj_name": "ท่อลอดข้ามถนน (ท่อคสล. ขนาด ? 1.00x1.00 ม. 3 แถวๆละ 10 ท่อน)",
                "LONG": 785664,
                "LAT": 1711413,
                "DEPARTMENT": "องค์กรปกครองส่วนท้องถิ่น",
                "BARRIER_": "ท่อระบายน้ำมีขนาดเล็กและฝังตื้น จึงเป็นอุปสรรคต่อการไหลของน้ำ",
                "YEAR": "",
                "STATUS": "รอตรวจสอบสถานะ",
                "Name": "ท่อลอด",
                "TAMBON_IDN": "360701",
                "TAM_NAM_T": "ต.บ้านชวน",
                "AMPHOE_T": "อ.บำเหน็จณรงค์",
                "PROV_NAM_T": "จ.ชัยภูมิ"
            }
        },
        {
            "type": "Feature",
            "geometry": {
                "type": "Point",
                "coordinates": [102.81249929655777, 16.374713357836082]
            },
            "properties": {
                "Prj_name": "ท่อระบายน้ำหมู่บ้านแหลม",
                "LONG": 907391,
                "LAT": 1814210,
                "DEPARTMENT": "องค์กรปกครองส่วนท้องถิ่น",
                "BARRIER_": "เนื่องจากบริเวณหมู่บ้านแหลมเป็นพื้นที่ลุ่มต่ำ  และติดกับแม่น้ำแม่กลอง  ในช่วงที่น้ำทะเลหนุน  จะทำให้น้ำในแม่น้ำแม่กลองไหลเข้าท่วมพื้นที่บริเวณหมู่บ้านแหลมเป็นประจำ (น้ำที่ไหลเข้าท่วมพื้นที่เป็นน้ำที่ไหลเข้ามาตามท่อระบายน้ำ)",
                "YEAR": "",
                "STATUS": "ติดปัญหาอุปสรรค ไม่สามารถดำเนินการได้",
                "Name": "ทรบ.",
                "TAMBON_IDN": "400106",
                "TAM_NAM_T": "ต.เมืองเก่า",
                "AMPHOE_T": "อ.เมืองขอนแก่น",
                "PROV_NAM_T": "จ.ขอนแก่น"
            }
        }
    ]
}